sqlpgq/__init__.py
sqlpgq/query.py
sqlpgq/schema.py
sqlpgq/types.py
sqlpgq-0.0.1.dist-info/METADATA
sqlpgq-0.0.1.dist-info/WHEEL
sqlpgq-0.0.1.dist-info/top_level.txt
sqlpgq-0.0.1.dist-info/RECORD
