Metadata-Version: 2.4
Name: sqlpgq
Version: 0.0.1
Summary: SQL/PGQ (Property Graph Queries) for Python
Author: James Cagalawan
License: GPL-3.0-or-later
Project-URL: Repository, https://github.com/cglwn/sqlpgq
Keywords: sql,pgq,graph,property-graph
Classifier: Development Status :: 3 - Alpha
Classifier: Intended Audience :: Developers
Classifier: Programming Language :: Python :: 3.12
Classifier: Topic :: Database
Requires-Python: >=3.12
Provides-Extra: dev
Requires-Dist: pytest>=7.0; extra == "dev"
Requires-Dist: pytest-cov>=4.0; extra == "dev"
Requires-Dist: mypy>=1.0; extra == "dev"
Requires-Dist: ruff>=0.1.0; extra == "dev"
